[
    {
        "id": "00001",
        "checkIns": {
            "October": {
                "17": "01:00",
                "18": "10:21",
                "22": "09:00"
            }
        }
    },
    {
        "id": "00002",
        "checkIns": {
            "October": {
                "17": "02:00",
                "18": "15:21",
                "19": "02:00",
                "20": "01:00"
            }
        }
    },
    {
        "id": "00003",
        "checkIns": {
            "October": {
                "17": "05:00",
                "18": "16:21",
                "19": "14:00"
            }
        }
    },
    {
        "id": "00005",
        "checkIns": {
            "October": {
                "17": "08:00",
                "18": "17:21",
                "19": "08:00"
            }
        }
    },
    {
        "id": "00006",
        "checkIns": {
            "October": {
                "17": "09:00",
                "18": "20:21",
                "19": "19:00",
                "20": "12:00",
                "21": "12:00"
            }
        }
    },
    {
        "id": "00007",
        "checkIns": {
            "October": {
                "17": "12:00",
                "18": "00:21",
                "19": "06:00",
                "21": "10:00"
            }
        }
    },
    {
        "id": "00008",
        "checkIns": {
            "October": {
                "17": "12:00",
                "18": "23:21",
                "19": "12:00",
                "20": "11:00"
            }
        }
    },
    {
        "id": "00009",
        "checkIns": {
            "October": {
                "17": "12:00",
                "18": "13:21",
                "19": "18:00"
            }
        }
    },
    {
        "id": "00010",
        "checkIns": {
            "October": {
                "17": "12:00",
                "18": "13:21",
                "19": "23:00",
                "21": "09:00"

            }
        }
    },
    {
        "id": "00011",
        "checkIns": {
            "October": {
                "17": "12:00",
                "18": "13:21",
                "19": "02:00"
            }
        }
    },
    {
        "id": "00012",
        "checkIns": {
            "October": {
                "17": "12:00",
                "18": "13:21",
                "19": "03:00",
                "22": "12:00"
            }
        }
    }
]